{
  "resourceType": "Organization",
  "id": "nice-org",
  "identifier": [
    {
      "system": "http://example.org/identificativo",
      "value": "12345"
    }
  ],
  "active": true,
  "name": "Fantastica Azienda",
  "telecom": [
    {
      "system": "phone",
      "value": "tel:+39 123 456 7890",
      "use": "mobile"
    },
    {
      "system": "email",
      "value": "mailto:info@nice-org.it",
      "use": "work"
    }
  ],
  "address": [
    {
      "line": [
        "1, Piazza Signoria"
      ],
      "city": "Firenze",
      "postalCode": "50100",
      "country": "IT"
    }
  ],
  "contact": [
    {
      "name": {
        "text": "Dott. Ivo Serbelloni Viendalmare"
      }
    }
  ]
}
